{
  "hotels": [
    {
      "name": "The Grand Hotel",
      "property_type": "Hotel",
      "location": "New York",
      "rating": 4.5,
      "star": 5,
      "price": 250,
      "sale_price": 200,
      "benefits": ["Free Wi-Fi", "Free Breakfast", "Fitness Center"],
      "comments": [
        "Beautiful hotel with great service and amenities.",
        "Highly recommend!",
        "Amazing view from the room.",
        "Great location."
      ],
      "coordinates": [40.7128, -74.0060],
      "image": "https://unsplash.com/photos/brown-concrete-building-near-green-trees-during-daytime-qhUCaOrwQuc"
    },
    {
      "name": "The Plaza Hotel",
      "property_type": "Hotel",
      "location": "Los Angeles",
      "rating": 4.0,
      "star": 4,
      "price": 300,
      "benefits": ["Free Wi-Fi", "Fitness Center", "Pool"],
      "comments": [
        "A bit pricey but worth it for the location and historic charm.",
        "Great staff and service.",
        "The room was a bit small."
      ],
      "coordinates": [34.0522, -118.2437],
      "image": "https://example.com/images/plaza-hotel.jpg"
    },
    {
      "name": "The Ritz Carlton",
      "property_type": "Hotel",
      "location": "Chicago",
      "rating": 5.0,
      "star": 5,
      "price": 500,
      "sale_price": 450,
      "benefits": [
        "Free Wi-Fi",
        "Free Breakfast",
        "Fitness Center",
        "Pool",
        "Spa"
      ],
      "comments": [
        "Absolutely luxurious hotel with top-notch service and amenities.",
        "The spa is amazing!",
        "Great location and view."
      ],
      "coordinates": [41.8781, -87.6298],
      "image": "https://example.com/images/ritz-carlton.jpg"
    },
    {
      "name": "The Waldorf Astoria",
      "property_type": "Hotel",
      "location": "Miami",
      "rating": 4.5,
      "star": 5,
      "price": 400,
      "sale_price": 350,
      "benefits": ["Free Wi-Fi", "Free Breakfast", "Fitness Center", "Pool"],
      "comments": [
        "Stunning hotel with impeccable service and a great spa.",
        "Great amenities and service.",
        "The room was a bit small."
      ],
      "coordinates": [25.7617, -80.1918],
      "image": "https://example.com/images/waldorf-astoria.jpg"
    },
    {
      "name": "The Four Seasons Hotel",
      "property_type": "Hotel",
      "location": "Las Vegas",
      "rating": 4.7,
      "star": 3,
      "price": 350,
      "sale_price": 300,
      "benefits": ["Free Wi-Fi", "Free Breakfast", "Fitness Center", "Pool"],
      "comments": [
        "Excellent hotel with great service and amenities.",
        "Highly recommend!",
        "Great location and view."
      ],
      "coordinates": [36.1699, -115.1398],
      "image": "https://example.com/images/four-seasons.jpg"
    },
    {
      "name": "Mock Up Hotel",
      "property_type": "Hotel",
      "location": "New York",
      "rating": 4.5,
      "star": 4,
      "comments": [
        "Fantastic hotel with great service.",
        "Clean and spacious rooms.",
        "Excellent location."
      ],
      "benefits": [
        "Free Wi-Fi",
        "On-site restaurant",
        "Fitness center",
        "Business center"
      ],
      "price": 200,
      "sale_price": 180,
      "coordinates": [40.7128, -74.0060],
      "image": "https://example.com/images/mock-up-hotel.jpg"
    },
    {
      "name": "Mock Up Resort",
      "property_type": "Resort",
      "location": "Los Angeles",
      "rating": 4.0,
      "star": 3,
      "comments": [
        "Beautiful resort with great amenities.",
        "Friendly staff and great service.",
        "Wonderful location near the beach."
      ],
      "benefits": [
        "Free Wi-Fi",
        "Spa and fitness center",
        "On-site restaurant",
        "Shuttle service to nearby attractions"
      ],
      "price": 350,
      "coordinates": [34.0522, -118.2437],
      "image": "https://example.com/images/mock-up-resort.jpg"
    },
    {
      "name": "Mock Up Inn",
      "property_type": "Inn",
      "location": "Chicago",
      "rating": 3.5,
      "star": 2,
      "comments": [
        "Charming inn with great character.",
        "Friendly staff and comfortable rooms.",
        "Great location in the city."
      ],
      "benefits": [
        "Free Wi-Fi",
        "Continental breakfast",
        "Bicycles available for rent"
      ],
      "price": 150,
      "coordinates": [41.8781, -87.6298],
      "image": "https://example.com/images/mock-up-inn.jpg"
    },
    {
      "name": "Mock Up Luxury Hotel",
      "property_type": "Luxury Hotel",
      "location": "Miami",
      "rating": 5.0,
      "star": 5,
      "comments": [
        "Exceptional luxury hotel with top-notch service.",
        "Beautiful rooms and gorgeous common areas.",
        "Fantastic location in the heart of the city."
      ],
      "benefits": [
        "Free Wi-Fi",
        "On-site spa and fitness center",
        "Room service",
        "Valet parking"
      ],
      "price": 450,
      "sale_price": 425,
      "coordinates": [25.7617, -80.1918],
      "image": "https://example.com/images/mock-up-luxury-hotel.jpg"
    },
    {
      "name": "Mock Up Boutique Hotel",
      "property_type": "Boutique Hotel",
      "location": "Las Vegas",
      "rating": 4.0,
      "star": 3,
      "comments": [
        "Charming boutique hotel with unique character.",
        "Friendly staff and well-appointed rooms.",
        "Great location in a trendy neighborhood."
      ],
      "benefits": [
        "Free Wi-Fi",
        "On-site bar and restaurant",
        "Pet-friendly",
        "24-hour front desk service"
      ],
      "price": 250,
      "coordinates": [36.1699, -115.1398],
      "image": "https://example.com/images/mock-up-boutique-hotel.jpg"
    },
    {
      "name": "Mock Up Budget Hotel",
      "property_type": "Budget Hotel",
      "location": "San Francisco",
      "rating": 3.0,
      "star": 2,
      "comments": [
        "Affordable budget hotel with basic amenities.",
        "Clean and comfortable rooms.",
        "Convenient location near public transportation."
      ],
      "benefits": [
        "Free Wi-Fi",
        "24-hour front desk service",
        "Continental breakfast"
      ],
      "price": 100,
      "coordinates": [37.7749, -122.4194],
      "image": "https://example.com/images/mock-up-budget-hotel.jpg"
    },
    {
      "name": "Mock Up Family Hotel",
      "property_type": "Family Hotel",
      "location": "Seattle",
      "rating": 4.5,
      "star": 4,
      "comments": [
        "Great hotel for families with kids.",
        "Spacious rooms and plenty of activities.",
        "Friendly staff and great service."
      ],
      "benefits": [
        "Free Wi-Fi",
        "On-site pool and playground",
        "Family-friendly activities and entertainment",
        "Babysitting service available"
      ],
      "price": 250,
      "sale_price": 225,
      "coordinates": [47.6062, -122.3321],
      "image": "https://example.com/images/mock-up-family-hotel.jpg"
    },
    {
      "name": "Mock Up Business Hotel",
      "property_type": "Business Hotel",
      "location": "Boston",
      "rating": 4.0,
      "star": 3,
      "comments": [
        "Great hotel for business travelers.",
        "Well-appointed rooms and great amenities.",
        "Convenient location near business district."
      ],
      "benefits": [
        "Free Wi-Fi",
        "Business center with meeting rooms",
        "On-site restaurant and bar",
        "24-hour front desk service"
      ],
      "price": 300,
      "coordinates": [42.3601, -71.0589],
      "image": "https://example.com/images/mock-up-business-hotel.jpg"
    },
    {
      "name": "Mock Up Beach Hotel",
      "property_type": "Beach Hotel",
      "location": "Los Angeles",
      "rating": 4.5,
      "star": 4,
      "comments": [
        "Beautiful beachside hotel with great views.",
        "Friendly staff and comfortable rooms.",
        "Great location near the beach."
      ],
      "benefits": [
        "Free Wi-Fi",
        "On-site pool and beach access",
        "Pet-friendly",
        "Free breakfast"
      ],
      "price": 350,
      "coordinates": [34.0522, -118.2437],
      "image": "https://example.com/images/mock-up-beach-hotel.jpg"
    }
  ]
}
